{"story_foldername": "galaxy_formation", "story_filename": "galaxy_formation", "story_title": "Galaxy Formation", "tagged_story_for_tts": "Cosmic dust clouds.<[silence:50ms]> Gravity sculpts them.<[silence:50ms]>\nThe name galaxy comes from the Greek gala, meaning milk, like the Milky Way\u2019s pale band across the night sky.<[silence:50ms]>\nA cloud of gas and dust drifts in space, nearly invisible.<[silence:50ms]> Gravity pulls particles together, like iron filings to a magnet.<[silence:50ms]> The cloud collapses, spinning faster as it shrinks, flattening into a disk.<[silence:50ms]> Stars ignite within it, their light revealing the new galaxy.<[silence:50ms]> The Andromeda Galaxy formed this way, its 1 trillion stars born from such a collapse.<[silence:50ms]>\nThree related subjects are dark matter, star clusters and cosmic inflation.<[silence:50ms]>", "clean_story": "Cosmic dust clouds. Gravity sculpts them.\nThe name galaxy comes from the Greek gala, meaning milk, like the Milky Way\u2019s pale band across the night sky.\nA cloud of gas and dust drifts in space, nearly invisible. Gravity pulls particles together, like iron filings to a magnet. The cloud collapses, spinning faster as it shrinks, flattening into a disk. Stars ignite within it, their light revealing the new galaxy. The Andromeda Galaxy formed this way, its 1 trillion stars born from such a collapse.\nThree related subjects are dark matter, star clusters and cosmic inflation.", "timestamp": "20260610T125810Z"}