{"story_foldername": "ninja_weaponry_evolution", "story_filename": "ninja_weaponry_evolution", "story_title": "Ninja Weaponry Evolution", "tagged_story_for_tts": "Silent tools.<[silence:200]> Adaptation over strength.<[silence:200]>\nNinja means \"one who endures\"\u2014fitting for weapons built to outlast detection, not brute force.<[silence:200]>\n\nEarly ninja repurposed farming tools:<[silence:120]> kama (sickles) became slashing weapons;<[silence:150]> kunai (digging spikes) turned into climbing hooks or thrown distractors.<[silence:200]> Like a crowbar used as both lever and club, simplicity hid intent.<[silence:200]> By the 15th century, shinobi shozoku (ninja gear) included makibishi (spiked caltrops)\u2014scattered like Lego pieces on a dark floor\u2014to slow pursuers without a sound.<[silence:200]>\n\nThe shuriken evolved from carpentry nails, flattened for aerodynamics.<[silence:200]> A 17th-century manual, Bansenshukai, details how blacksmiths folded iron into star-shaped blades that spun true when thrown sidearm\u2014like skipping stones, but lethal.<[silence:200]> Smoke bombs (enmaku) used gunpowder wrapped in egg membranes;<[silence:150]> the thin skin burned fast, creating instant cover.<[silence:200]>\n\nThree related subjects are feudal espionage tools, metallurgy in covert warfare, and how terrain shaped stealth.<[silence:200]>", "clean_story": "Silent tools. Adaptation over strength.\nNinja means \"one who endures\"\u2014fitting for weapons built to outlast detection, not brute force.\n\nEarly ninja repurposed farming tools: kama (sickles) became slashing weapons; kunai (digging spikes) turned into climbing hooks or thrown distractors. Like a crowbar used as both lever and club, simplicity hid intent. By the 15th century, shinobi shozoku (ninja gear) included makibishi (spiked caltrops)\u2014scattered like Lego pieces on a dark floor\u2014to slow pursuers without a sound.\n\nThe shuriken evolved from carpentry nails, flattened for aerodynamics. A 17th-century manual, Bansenshukai, details how blacksmiths folded iron into star-shaped blades that spun true when thrown sidearm\u2014like skipping stones, but lethal. Smoke bombs (enmaku) used gunpowder wrapped in egg membranes; the thin skin burned fast, creating instant cover.\n\nThree related subjects are feudal espionage tools, metallurgy in covert warfare, and how terrain shaped stealth.", "timestamp": "20260422T200641Z"}