{"story_foldername": "how_writing_shapes_power", "story_filename": "how_writing_shapes_power", "story_title": "How Writing Shapes Power", "tagged_story_for_tts": "Words as levers.<[silence:60ms]> Power built on ink.<[silence:60ms]>\n\nThe phrase \"writing shapes power\" fits because written words, unlike speech, freeze ideas in time\u2014turning fleeting commands into permanent rules.<[silence:60ms]> Like a carpenter\u2019s chisel carving wood into furniture, writing carves chaos into law.<[silence:60ms]>\n\nBefore writing, power relied on memory and force.<[silence:60ms]> A king\u2019s decree died with the messenger;<[silence:40ms]> a tribe\u2019s history twisted with each retelling.<[silence:60ms]> Then came cuneiform in Mesopotamia, 3200 BCE: clay tablets recording grain taxes.<[silence:60ms]> Suddenly, a scribe\u2019s stylus could outlast a ruler\u2019s voice.<[silence:60ms]> Laws like Hammurabi\u2019s Code (1754 BCE) weren\u2019t just spoken\u2014they were displayed, etched in stone for all to see (or fear).<[silence:60ms]> The shift was mechanical: ink on papyrus or chalk on slate acted like a ratchet, locking authority in place.<[silence:60ms]> No need to repeat orders when they\u2019re hung in the town square.<[silence:60ms]>\n\nFast forward to 1439: Gutenberg\u2019s press.<[silence:60ms]> Before, a Bible took a monk years to copy;<[silence:40ms]> now, 180 could print in a day.<[silence:60ms]> Martin Luther\u2019s 95 Theses (1517) spread across Germany in weeks\u2014not because he shouted louder, but because movable type amplified his words like a megaphone.<[silence:60ms]> Power wasn\u2019t just preserved;<[silence:40ms]> it was scaled.<[silence:60ms]> Governments noticed.<[silence:60ms]> By 1644, England\u2019s Parliament used printed pamphlets to rally support against King Charles I. Words didn\u2019t just record power\u2014they redistributed it.<[silence:60ms]>\n\nToday?<[silence:55ms]> Algorithms sort resumes by keywords;<[silence:40ms]> a tweet topples stock markets;<[silence:40ms]> a leaked memo ends careers.<[silence:60ms]> Writing still works like a lever: short strokes move heavy weights.<[silence:60ms]>\n\nThree related subjects are propaganda\u2019s printed roots, how signatures bind contracts, and silence as power\u2019s tool.<[silence:60ms]>", "clean_story": "Words as levers. Power built on ink.\n\nThe phrase \"writing shapes power\" fits because written words, unlike speech, freeze ideas in time\u2014turning fleeting commands into permanent rules. Like a carpenter\u2019s chisel carving wood into furniture, writing carves chaos into law.\n\nBefore writing, power relied on memory and force. A king\u2019s decree died with the messenger; a tribe\u2019s history twisted with each retelling. Then came cuneiform in Mesopotamia, 3200 BCE: clay tablets recording grain taxes. Suddenly, a scribe\u2019s stylus could outlast a ruler\u2019s voice. Laws like Hammurabi\u2019s Code (1754 BCE) weren\u2019t just spoken\u2014they were displayed, etched in stone for all to see (or fear). The shift was mechanical: ink on papyrus or chalk on slate acted like a ratchet, locking authority in place. No need to repeat orders when they\u2019re hung in the town square.\n\nFast forward to 1439: Gutenberg\u2019s press. Before, a Bible took a monk years to copy; now, 180 could print in a day. Martin Luther\u2019s 95 Theses (1517) spread across Germany in weeks\u2014not because he shouted louder, but because movable type amplified his words like a megaphone. Power wasn\u2019t just preserved; it was scaled. Governments noticed. By 1644, England\u2019s Parliament used printed pamphlets to rally support against King Charles I. Words didn\u2019t just record power\u2014they redistributed it.\n\nToday? Algorithms sort resumes by keywords; a tweet topples stock markets; a leaked memo ends careers. Writing still works like a lever: short strokes move heavy weights.\n\nThree related subjects are propaganda\u2019s printed roots, how signatures bind contracts, and silence as power\u2019s tool.", "timestamp": "20260604T201445Z"}