{
  "story_filename": "the_baobab_",
  "story_title": "The Baobab ",
  "tagged_story_for_tts": "\"Resilient giants.<[silence]> Unique ecosystems.<[silence]> The word 'baobab' originates from the Arabic 'bu hibab,' meaning 'fruit with many seeds.'<[silence]> Baobabs, native to Madagascar, Africa, and Australia, are renowned for their enormous trunks and longevity, often living for over a thousand years.<[silence]> These trees store thousands of liters of water in their trunks, enabling survival in arid climates where other flora wither.<[silence]>\\n\\nBaobabs serve as critical resources for local communities, providing shelter, food, and water.<[silence]> Their fruit, known as 'monkey bread,' is rich in vitamin C and antioxidants, while their bark can be used to make rope and cloth.<[silence]> In Madagascar, baobabs form 'avenues,' creating stunning landscapes that attract tourists and support local economies.<[silence]>\\n\\nTheir hollow trunks often house animals and even humans, offering refuge in harsh environments.<[silence]> Despite their resilience, baobabs face threats from climate change and deforestation, which can disrupt their growth and reproduction.<[silence]> Conservation efforts are crucial to preserve these iconic trees and the ecosystems they support.<[silence]>\\n\\nThree related subjects are the impact of climate change on ancient tree species, the role of traditional knowledge in conservation, and the ecological significance of keystone species like the baobab.<[silence]>\"",
  "clean_story": "\"Resilient giants. Unique ecosystems. The word 'baobab' originates from the Arabic 'bu hibab,' meaning 'fruit with many seeds. ' Baobabs, native to Madagascar, Africa, and Australia, are renowned for their enormous trunks and longevity, often living for over a thousand years. These trees store thousands of liters of water in their trunks, enabling survival in arid climates where other flora wither. \\n\\nBaobabs serve as critical resources for local communities, providing shelter, food, and water. Their fruit, known as 'monkey bread,' is rich in vitamin C and antioxidants, while their bark can be used to make rope and cloth. In Madagascar, baobabs form 'avenues,' creating stunning landscapes that attract tourists and support local economies. \\n\\nTheir hollow trunks often house animals and even humans, offering refuge in harsh environments. Despite their resilience, baobabs face threats from climate change and deforestation, which can disrupt their growth and reproduction. Conservation efforts are crucial to preserve these iconic trees and the ecosystems they support. \\n\\nThree related subjects are the impact of climate change on ancient tree species, the role of traditional knowledge in conservation, and the ecological significance of keystone species like the baobab. \"",
  "timestamp": "20251216T001011Z"
}